LearnJavascriptZhongwenban/README.md
LearnJavascriptZhongwenban/__init__.py
LearnJavascriptZhongwenban/__main__.py
LearnJavascriptZhongwenban/file.epub
LearnJavascriptZhongwenban/index.html
LearnJavascriptZhongwenban/css/__init__.py
LearnJavascriptZhongwenban/css/annotations.css
LearnJavascriptZhongwenban/css/main.css
LearnJavascriptZhongwenban/css/normalize.css
LearnJavascriptZhongwenban/css/popup.css
LearnJavascriptZhongwenban/font/__init__.py
LearnJavascriptZhongwenban/font/fontello.eot
LearnJavascriptZhongwenban/font/fontello.svg
LearnJavascriptZhongwenban/font/fontello.ttf
LearnJavascriptZhongwenban/font/fontello.woff
LearnJavascriptZhongwenban/img/__init__.py
LearnJavascriptZhongwenban/img/annotator-glyph-sprite.png
LearnJavascriptZhongwenban/img/annotator-icon-sprite.png
LearnJavascriptZhongwenban/img/apple-touch-icon.png
LearnJavascriptZhongwenban/img/cancelfullscreen.png
LearnJavascriptZhongwenban/img/close.png
LearnJavascriptZhongwenban/img/fullscreen.png
LearnJavascriptZhongwenban/img/loader.gif
LearnJavascriptZhongwenban/img/menu-icon.png
LearnJavascriptZhongwenban/img/save.png
LearnJavascriptZhongwenban/img/saved.png
LearnJavascriptZhongwenban/img/settings-s.png
LearnJavascriptZhongwenban/img/settings.png
LearnJavascriptZhongwenban/img/star.png
LearnJavascriptZhongwenban/js/__init__.py
LearnJavascriptZhongwenban/js/epub.js
LearnJavascriptZhongwenban/js/epub.min.js
LearnJavascriptZhongwenban/js/epub.min.map
LearnJavascriptZhongwenban/js/hooks.min.js
LearnJavascriptZhongwenban/js/hooks.min.map
LearnJavascriptZhongwenban/js/reader.js
LearnJavascriptZhongwenban/js/reader.js.map
LearnJavascriptZhongwenban/js/reader.min.js
LearnJavascriptZhongwenban/js/reader.min.map
LearnJavascriptZhongwenban/js/hooks/__init__.py
LearnJavascriptZhongwenban/js/hooks/extensions/__init__.py
LearnJavascriptZhongwenban/js/hooks/extensions/highlight.js
LearnJavascriptZhongwenban/js/libs/__init__.py
LearnJavascriptZhongwenban/js/libs/jquery.min.js
learn_javascript_zhongwenban-2024.3.1.0.dist-info/METADATA
learn_javascript_zhongwenban-2024.3.1.0.dist-info/WHEEL
learn_javascript_zhongwenban-2024.3.1.0.dist-info/entry_points.txt
learn_javascript_zhongwenban-2024.3.1.0.dist-info/top_level.txt
learn_javascript_zhongwenban-2024.3.1.0.dist-info/RECORD
